pyrevolt/__init__.py
pyrevolt/bot.py
pyrevolt/client.py
pyrevolt/events.py
pyrevolt/exceptions.py
pyrevolt/gateway.py
pyrevolt/session.py
pyrevolt/structs/channels.py
pyrevolt/structs/invite.py
pyrevolt/structs/member.py
pyrevolt/structs/server.py
pyrevolt/structs/user.py
pyrevolt-0.2.9.dev0.data/data/requirements.txt
pyrevolt-0.2.9.dev0.dist-info/LICENSE
pyrevolt-0.2.9.dev0.dist-info/METADATA
pyrevolt-0.2.9.dev0.dist-info/WHEEL
pyrevolt-0.2.9.dev0.dist-info/top_level.txt
pyrevolt-0.2.9.dev0.dist-info/RECORD
