Metadata-Version: 2.1
Name: pyrevolt
Version: 0.2.9.dev0
Summary: A Python library to wrap the Revolt API, made to be easy-to-use but powerful and feature rich.
Home-page: https://github.com/GenericNerd/pyrevolt
Author: Fabio Almeida
Author-email: me@fabioalmeida.dev
License: MIT
Project-URL: Source Code, https://github.com/GenericNerd/pyrevolt
Project-URL: Bug Tracker, https://github.com/GenericNerd/pyrevolt/issues
Classifier: Development Status :: 2 - Pre-Alpha
Classifier: License :: OSI Approved :: MIT License
Classifier: Natural Language :: English
Classifier: Operating System :: OS Independent
Classifier: Programming Language :: Python :: 3.10
Classifier: Topic :: Internet
Classifier: Topic :: Software Development :: Libraries
Classifier: Topic :: Software Development :: Libraries :: Python Modules
Classifier: Topic :: Utilities
Classifier: Typing :: Typed
Requires-Python: >=3.10
License-File: LICENSE
Requires-Dist: aiohttp
Requires-Dist: websockets
